sinhala_subtitle/__init__.py
sinhala_subtitle-3.0.1.dist-info/METADATA
sinhala_subtitle-3.0.1.dist-info/WHEEL
sinhala_subtitle-3.0.1.dist-info/top_level.txt
sinhala_subtitle-3.0.1.dist-info/RECORD
