Metadata-Version: 2.1
Name: sinhala-subtitle
Version: 3.0.1
Summary: This Python library is designed to make downloading Sinhala subtitles for TV series and movies easy. To use it, simply install the library using pip and import it into your Python script.
Home-page: 
Author: Gavindu Tharaka
Author-email: gavi.tharaka@gmail.com
Classifier: Programming Language :: Python :: 3
Classifier: License :: OSI Approved :: MIT License
Classifier: Operating System :: OS Independent
Requires-Dist: bs4
